MANIFEST.in
Makefile
README.rst
setup.cfg
setup.py
dojo/__init__.py
dojo/forms.py
dojo/task1.py
dojo/task2.py
dojo/views.py
dojo/features/environment.py
dojo/features/task1.feature
dojo/features/task2.feature
dojo/features/steps/groups.py
dojo/features/steps/parse.py
dojo/static/css/normalize.css
dojo/static/css/style.css
dojo/static/img/ninja.png
dojo/templates/base.html
dojo/templates/index.html
dojo/templates/task.html
dojo/templates/task1.html
dojo/templates/task2.html
dojo/tests/__init__.py
dojo/tests/test_field.py
dojo/tests/test_parser.py
dojo/tests/test_views.py
thoreg_dojo.egg-info/PKG-INFO
thoreg_dojo.egg-info/SOURCES.txt
thoreg_dojo.egg-info/dependency_links.txt
thoreg_dojo.egg-info/not-zip-safe
thoreg_dojo.egg-info/requires.txt
thoreg_dojo.egg-info/top_level.txt