Metadata-Version: 1.1
Name: thoreg-dojo
Version: 0.5
Summary: The coding dojo of Thoreg
Home-page: https://github.com/thoreg/dojo
Author: Thomas Rega
Author-email: thoreg@gmail.com
License: BSD
Keywords: dojo,thoreg,examples,flask,behave,tests
Platform: UNKNOWN
Classifier: Programming Language :: Python
Classifier: Programming Language :: Python :: 2
Classifier: Programming Language :: Python :: 2.7
Classifier: Topic :: Software Development :: User Interfaces
